tilesegy/__init__.py
tilesegy/cli.py
tilesegy/convert.py
tilesegy/indexables.py
tilesegy/singledispatchmethod.py
tilesegy/utils.py
tilesegy-0.1.0.dist-info/LICENSE
tilesegy-0.1.0.dist-info/METADATA
tilesegy-0.1.0.dist-info/WHEEL
tilesegy-0.1.0.dist-info/entry_points.txt
tilesegy-0.1.0.dist-info/top_level.txt
tilesegy-0.1.0.dist-info/RECORD
