Metadata-Version: 2.1
Name: tilesegy
Version: 0.1.0
Summary: Python library for fast access to seismic data using TileDB
Home-page: https://github.com/gsakkis/tilesegy
Author: George Sakkis
Author-email: george.sakkis@gmail.com
License: MIT
Platform: UNKNOWN
Classifier: Development Status :: 3 - Alpha
Classifier: Environment :: Other Environment
Classifier: Intended Audience :: Developers
Classifier: Intended Audience :: Science/Research
Classifier: License :: OSI Approved :: MIT License
Classifier: Natural Language :: English
Classifier: Programming Language :: Python
Classifier: Programming Language :: Python :: 3
Classifier: Programming Language :: Python :: 3.6
Classifier: Programming Language :: Python :: 3.7
Classifier: Programming Language :: Python :: 3.8
Classifier: Topic :: Scientific/Engineering
Classifier: Topic :: Scientific/Engineering :: Physics
Classifier: Topic :: Software Development :: Libraries
Classifier: Topic :: Utilities
Requires-Dist: cached-property
Requires-Dist: segyio (>=1.9.3)
Requires-Dist: tiledb
